AutoParam/__init__.py
AutoParam-0.0.1.dist-info/METADATA
AutoParam-0.0.1.dist-info/RECORD
AutoParam-0.0.1.dist-info/WHEEL
AutoParam-0.0.1.dist-info/top_level.txt
